{
  "$schema": "https://developer.microsoft.com/json-schemas/fabric/item/report/definition/visualContainerMobileState/2.2.0/schema.json",
  "position": {
    "x": 0,
    "y": 73,
    "z": 18000,
    "height": 55,
    "width": 135,
    "tabOrder": 18000
  },
  "objects": {
    "header": [
      {
        "properties": {
          "textSize": {
            "expr": {
              "Literal": {
                "Value": "10D"
              }
            }
          },
          "outlineStyle": {
            "expr": {
              "Literal": {
                "Value": "4D"
              }
            }
          }
        }
      }
    ],
    "items": [
      {
        "properties": {
          "textSize": {
            "expr": {
              "Literal": {
                "Value": "9D"
              }
            }
          },
          "padding": {
            "expr": {
              "Literal": {
                "Value": "1D"
              }
            }
          }
        }
      }
    ],
    "general": [
      {
        "properties": {
          "outlineWeight": {
            "expr": {
              "Literal": {
                "Value": "2D"
              }
            }
          },
          "outlineColor": {
            "solid": {
              "color": {
                "expr": {
                  "Literal": {
                    "Value": "'#153B8B'"
                  }
                }
              }
            }
          }
        }
      }
    ],
    "pendingChangesIcon": [
      {
        "properties": {
          "size": {
            "expr": {
              "Literal": {
                "Value": "8D"
              }
            }
          }
        }
      }
    ],
    "data": [],
    "selection": []
  },
  "visualContainerObjects": {
    "padding": [
      {
        "properties": {
          "top": {
            "expr": {
              "Literal": {
                "Value": "2D"
              }
            }
          },
          "right": {
            "expr": {
              "Literal": {
                "Value": "1D"
              }
            }
          },
          "left": {
            "expr": {
              "Literal": {
                "Value": "1D"
              }
            }
          },
          "bottom": {
            "expr": {
              "Literal": {
                "Value": "1D"
              }
            }
          }
        }
      }
    ]
  }
}